[
  {
    "name": "HTML/CSS/JS unquoted attribute value validator",
    "desc": "Validate unquoted attribute values in HTML, CSS, and JavaScript code.",
    "slug": "unquoted-attributes",
    "logo": "",
    "link": "./tools/unquoted-attributes",
    "title": "HTML/CSS/JS Unquoted Attribute Value Validator",
    "keywords": ["HTML", "CSS", "JS", "validator", "attribute", "unquoted"],
    "views": "4k"
  },
  {
    "name": "Ambiguous ampersand checker for HTML",
    "desc": "Check for ambiguous ampersands in HTML code.",
    "slug": "ampersands",
    "logo": "",
    "link": "./tools/ampersands",
    "title": "Ambiguous Ampersand Checker for HTML",
    "keywords": ["HTML", "ampersand", "checker"],
    "views": "48k"
  },
  {
    "name": "Custom HTML element name validator",
    "desc": "Validate custom HTML element names.",
    "slug": "custom-element-name",
    "logo": "",
    "link": "./tools/custom-element-name",
    "title": "Custom HTML Element Name Validator",
    "keywords": ["HTML", "validator", "element name"],
    "views": "64k"
  },
  {
    "name": "CSS escaper",
    "desc": "Escape special characters in CSS code.",
    "slug": "css-escapes",
    "logo": "",
    "link": "./tools/css-escapes",
    "title": "CSS Escaper",
    "keywords": ["CSS", "escaper", "escape"],
    "views": "41k"
  },
  {
    "name": "Unquoted CSS font family name validator",
    "desc": "Validate unquoted font family names in CSS code.",
    "slug": "font-family",
    "logo": "",
    "link": "./tools/font-family",
    "title": "Unquoted CSS Font Family Name Validator",
    "keywords": ["CSS", "font", "family", "validator"],
    "views": "42k"
  },
  {
    "name": "JavaScript escaper",
    "desc": "Escape special characters in JavaScript code.",
    "slug": "js-escapes",
    "logo": "",
    "link": "./tools/js-escapes",
    "title": "JavaScript Escaper",
    "keywords": ["JavaScript", "escaper", "escape"],
    "views": "43k"
  },
  {
    "name": "JavaScript operator precedence",
    "desc": "Check operator precedence in JavaScript expressions.",
    "slug": "operator-precedence",
    "logo": "",
    "link": "./tools/operator-precedence",
    "title": "JavaScript Operator Precedence",
    "keywords": ["JavaScript", "operator", "precedence", "checker"],
    "views": "44k"
  },
  {
    "name": "JavaScript variable name validator",
    "desc": "Validate JavaScript variable names.",
    "slug": "js-variables",
    "logo": "",
    "link": "./tools/js-variables",
    "title": "JavaScript Variable Name Validator",
    "keywords": ["JavaScript", "validator", "variable", "name"],
    "views": "45k"
  },
  {
    "name": "JavaScript property name validator",
    "desc": "Validate JavaScript property names.",
    "slug": "js-properties",
    "logo": "",
    "link": "./tools/js-properties",
    "title": "JavaScript Property Name Validator",
    "keywords": ["JavaScript", "validator", "property", "name"],
    "views": "46k"
  },
  {
    "name": "Punycode IDN domain name converter",
    "desc": "Convert Punycode IDN domain names.",
    "slug": "punycode",
    "logo": "",
    "link": "./tools/punycode",
    "title": "Punycode IDN Domain Name Converter",
    "keywords": ["Punycode", "IDN", "domain", "converter"],
    "views": "47k"
  },
  {
    "name": "HTML entity encoder/decoder",
    "desc": "Encode and decode HTML entities.",
    "slug": "html-entities",
    "logo": "",
    "link": "./tools/html-entities",
    "title": "HTML Entity Encoder/Decoder",
    "keywords": ["HTML", "encoder", "decoder", "entities"],
    "views": "48k"
  },
  {
    "name": "URL encoder/decoder",
    "desc": "Encode and decode URLs.",
    "slug": "url",
    "logo": "",
    "link": "./tools/url",
    "title": "URL Encoder/Decoder",
    "keywords": ["URL", "encoder", "decoder"],
    "views": "49k"
  },
  {
    "name": "Legacy HTML color value previewer",
    "desc": "Preview legacy HTML color values (e.g., bgcolor, text, link, vlink, alink attributes).",
    "slug": "bgcolor",
    "logo": "",
    "link": "./tools/bgcolor",
    "title": "Legacy HTML Color Value Previewer",
    "keywords": ["HTML", "color", "previewer", "legacy"],
    "views": "50k"
  },
  {
    "name": "Base64 encoder/decoder",
    "desc": "Encode and decode Base64 data.",
    "slug": "base64",
    "logo": "",
    "link": "./tools/base64",
    "title": "Base64 Encoder/Decoder",
    "keywords": ["Base64", "encoder", "decoder"],
    "views": "51k"
  },
  {
    "name": "UTF-8 encoder/decoder",
    "desc": "Encode and decode UTF-8 data.",
    "slug": "utf-8",
    "logo": "",
    "link": "./tools/utf-8",
    "title": "UTF-8 Encoder/Decoder",
    "keywords": ["UTF-8", "encoder", "decoder"],
    "views": "52k"
  },
  {
    "name": "WTF-8 encoder/decoder",
    "desc": "Encode and decode WTF-8 data.",
    "slug": "wtf-8",
    "logo": "",
    "link": "./tools/wtf-8",
    "title": "WTF-8 Encoder/Decoder",
    "keywords": ["WTF-8", "encoder", "decoder"],
    "views": "53k"
  },
  {
    "name": "Quoted-Printable encoder/decoder",
    "desc": "Encode and decode Quoted-Printable data.",
    "slug": "quoted-printable",
    "logo": "",
    "link": "./tools/quoted-printable",
    "title": "Quoted-Printable Encoder/Decoder",
    "keywords": ["Quoted-Printable", "encoder", "decoder"],
    "views": "54k"
  },
  {
    "name": "Q encoder/decoder",
    "desc": "Encode and decode Q-encoded data.",
    "slug": "q",
    "logo": "",
    "link": "./tools/q",
    "title": "Q Encoder/Decoder",
    "keywords": ["Q", "encoder", "decoder"],
    "views": "55k"
  },
  {
    "name": "Binary ↔ ASCII converter",
    "desc": "Convert between binary and ASCII data.",
    "slug": "binary-ascii",
    "logo": "",
    "link": "./tools/binary-ascii",
    "title": "Binary ↔ ASCII Converter",
    "keywords": ["binary", "ASCII", "converter"],
    "views": "56k"
  },
  {
    "name": "Bacon’s cipher encoder/decoder",
    "desc": "Encode and decode text using Bacon's cipher.",
    "slug": "bacon",
    "logo": "",
    "link": "./tools/bacon",
    "title": "Bacon’s Cipher Encoder/Decoder",
    "keywords": ["Bacon's cipher", "encoder", "decoder"],
    "views": "57k"
  },
  {
    "name": "JavaScript regular expression transpiler",
    "desc": "Transpile JavaScript regular expressions.",
    "slug": "regexpu",
    "logo": "",
    "link": "./tools/regexpu",
    "title": "JavaScript Regular Expression Transpiler",
    "keywords": ["JavaScript", "regular expression", "transpiler"],
    "views": "58k"
  },
  {
    "name": "String reverser",
    "desc": "Reverse strings.",
    "slug": "reverse-string",
    "logo": "",
    "link": "./tools/reverse-string",
    "title": "String Reverser",
    "keywords": ["string", "reverser"],
    "views": "59k"
  },
  {
    "name": "String length & UTF-8 byte counter",
    "desc": "Count string length and UTF-8 bytes.",
    "slug": "byte-counter",
    "logo": "",
    "link": "./tools/byte-counter",
    "title": "String Length & UTF-8 Byte Counter",
    "keywords": ["string", "length", "UTF-8", "byte", "counter"],
    "views": "60k"
  },
  {
    "name": "Lua minifier",
    "desc": "Minify Lua code.",
    "slug": "lua-minifier",
    "logo": "",
    "link": "./tools/lua-minifier",
    "title": "Lua Minifier",
    "keywords": ["Lua", "minifier"],
    "views": "61k"
  },
  {
    "name": "Brainfuck minifier",
    "desc": "Minify Brainfuck code.",
    "slug": "brainfuck-minifier",
    "logo": "",
    "link": "./tools/brainfuck-minifier",
    "title": "Brainfuck Minifier",
    "keywords": ["Brainfuck", "minifier"],
    "views": "62k"
  },
  {
    "name": "Twitalics",
    "desc": "Convert text to italicized form.",
    "slug": "twitalics",
    "logo": "",
    "link": "./tools/twitalics",
    "title": "Twitalics",
    "keywords": ["Twitalics", "italic", "converter"],
    "views": "63k"
  },
  {
    "name": "Markdown to HTML Convertor",
    "desc": "Convert Markdown to HTML.",
    "slug": "markdown-to-html",
    "logo": "",
    "link": "./tools/markdown-to-html",
    "title": "Markdown to HTML Convertor",
    "keywords": ["Markdown", "HTML", "converter"],
    "views": "4k"
  },
  {
    "name": "JPG to PNG Convertor",
    "desc": "Convert JPG images to PNG format.",
    "slug": "jpg-to-png",
    "logo": "",
    "link": "./tools/jpg-to-png",
    "title": "JPG to PNG Convertor",
    "keywords": ["JPG", "PNG", "converter"],
    "views": "48k"
  },
  {
    "name": "JavaScript Minifier",
    "desc": "Minify JavaScript code.",
    "slug": "js-minifier",
    "logo": "",
    "link": "./tools/js-minifier",
    "title": "JavaScript Minifier",
    "keywords": ["JavaScript", "minifier"],
    "views": "64k"
  },
  {
    "name": "JavaScript Obfuscator",
    "desc": "Obfuscate JavaScript code.",
    "slug": "js-obfuscator",
    "logo": "",
    "link": "./tools/js-obfuscator",
    "title": "JavaScript Obfuscator",
    "keywords": ["JavaScript", "obfuscator"],
    "views": "41k"
  },
  {
    "name": "HTML to JSX Convertor",
    "desc": "Convert HTML to JSX.",
    "slug": "html-to-jsx",
    "logo": "",
    "link": "./tools/html-to-jsx",
    "title": "HTML to JSX Convertor",
    "keywords": ["HTML", "JSX", "converter"],
    "views": "42k"
  },
  {
    "name": "Markdown Editor",
    "desc": "Edit Markdown documents.",
    "slug": "markdown-editor",
    "logo": "",
    "link": "./tools/markdown-editor",
    "title": "Markdown Editor",
    "keywords": ["Markdown", "editor"],
    "views": "43k"
  },
  {
    "name": "Code Editor",
    "desc": "Edit code snippets.",
    "slug": "code-editor",
    "logo": "",
    "link": "./tools/code-editor",
    "title": "Code Editor",
    "keywords": ["code", "editor"],
    "views": "44k"
  },
  {
    "name": "WTF-8 Encoder/Decoder",
    "desc": "Encode and decode data using the WTF-8 encoding.",
    "slug": "wtf-8",
    "logo": "",
    "link": "./tools/wtf-8",
    "title": "WTF-8 Encoder/Decoder",
    "keywords": ["WTF-8", "encoder", "decoder"],
    "views": "53k"
  },
  {
    "name": "Quoted-Printable encoder/decoder",
    "desc": "Encode and decode Quoted-Printable data.",
    "slug": "quoted-printable",
    "logo": "",
    "link": "./tools/quoted-printable",
    "title": "Quoted-Printable Encoder/Decoder",
    "keywords": ["Quoted-Printable", "encoder", "decoder"],
    "views": "54k"
  },
  {
    "name": "Q encoder/decoder",
    "desc": "Encode and decode Q-encoded data.",
    "slug": "q",
    "logo": "",
    "link": "./tools/q",
    "title": "Q Encoder/Decoder",
    "keywords": ["Q", "encoder", "decoder"],
    "views": "55k"
  },
  {
    "name": "Binary ↔ ASCII converter",
    "desc": "Convert between binary and ASCII data.",
    "slug": "binary-ascii",
    "logo": "",
    "link": "./tools/binary-ascii",
    "title": "Binary ↔ ASCII Converter",
    "keywords": ["binary", "ASCII", "converter"],
    "views": "56k"
  },
  {
    "name": "Bacon’s cipher encoder/decoder",
    "desc": "Encode and decode text using Bacon's cipher.",
    "slug": "bacon",
    "logo": "",
    "link": "./tools/bacon",
    "title": "Bacon’s Cipher Encoder/Decoder",
    "keywords": ["Bacon's cipher", "encoder", "decoder"],
    "views": "57k"
  },
  {
    "name": "JavaScript regular expression transpiler",
    "desc": "Transpile JavaScript regular expressions.",
    "slug": "regexpu",
    "logo": "",
    "link": "./tools/regexpu",
    "title": "JavaScript Regular Expression Transpiler",
    "keywords": ["JavaScript", "regular expression", "transpiler"],
    "views": "58k"
  },
  {
    "name": "String reverser",
    "desc": "Reverse strings.",
    "slug": "reverse-string",
    "logo": "",
    "link": "./tools/reverse-string",
    "title": "String Reverser",
    "keywords": ["string", "reverser"],
    "views": "59k"
  },
  {
    "name": "String length & UTF-8 byte counter",
    "desc": "Count string length and UTF-8 bytes.",
    "slug": "byte-counter",
    "logo": "",
    "link": "./tools/byte-counter",
    "title": "String Length & UTF-8 Byte Counter",
    "keywords": ["string", "length", "UTF-8", "byte", "counter"],
    "views": "60k"
  },
  {
    "name": "Lua minifier",
    "desc": "Minify Lua code.",
    "slug": "lua-minifier",
    "logo": "",
    "link": "./tools/lua-minifier",
    "title": "Lua Minifier",
    "keywords": ["Lua", "minifier"],
    "views": "61k"
  },
  {
    "name": "Brainfuck minifier",
    "desc": "Minify Brainfuck code.",
    "slug": "brainfuck-minifier",
    "logo": "",
    "link": "./tools/brainfuck-minifier",
    "title": "Brainfuck Minifier",
    "keywords": ["Brainfuck", "minifier"],
    "views": "62k"
  },
  {
    "name": "Twitalics",
    "desc": "Convert text to italicized form.",
    "slug": "twitalics",
    "logo": "",
    "link": "./tools/twitalics",
    "title": "Twitalics",
    "keywords": ["Twitalics", "italic", "converter"],
    "views": "63k"
  },
  {
    "name": "Markdown to HTML Convertor",
    "desc": "Convert Markdown to HTML.",
    "slug": "markdown-to-html",
    "logo": "",
    "link": "./tools/markdown-to-html",
    "title": "Markdown to HTML Convertor",
    "keywords": ["Markdown", "HTML", "converter"],
    "views": "4k"
  },
  {
    "name": "JPG to PNG Convertor",
    "desc": "Convert JPG images to PNG format.",
    "slug": "jpg-to-png",
    "logo": "",
    "link": "./tools/jpg-to-png",
    "title": "JPG to PNG Convertor",
    "keywords": ["JPG", "PNG", "converter"],
    "views": "48k"
  },
  {
    "name": "JavaScript Minifier",
    "desc": "Minify JavaScript code.",
    "slug": "js-minifier",
    "logo": "",
    "link": "./tools/js-minifier",
    "title": "JavaScript Minifier",
    "keywords": ["JavaScript", "minifier"],
    "views": "64k"
  },
  {
    "name": "JavaScript Obfuscator",
    "desc": "Obfuscate JavaScript code.",
    "slug": "js-obfuscator",
    "logo": "",
    "link": "./tools/js-obfuscator",
    "title": "JavaScript Obfuscator",
    "keywords": ["JavaScript", "obfuscator"],
    "views": "41k"
  },
  {
    "name": "HTML to JSX Convertor",
    "desc": "Convert HTML to JSX.",
    "slug": "html-to-jsx",
    "logo": "",
    "link": "./tools/html-to-jsx",
    "title": "HTML to JSX Convertor",
    "keywords": ["HTML", "JSX", "converter"],
    "views": "42k"
  },
  {
    "name": "Markdown Editor",
    "desc": "Edit Markdown documents.",
    "slug": "markdown-editor",
    "logo": "",
    "link": "./tools/markdown-editor",
    "title": "Markdown Editor",
    "keywords": ["Markdown", "editor"],
    "views": "43k"
  },
  {
    "name": "Code Editor",
    "desc": "Edit code snippets.",
    "slug": "code-editor",
    "logo": "",
    "link": "./tools/code-editor",
    "title": "Code Editor",
    "keywords": ["code", "editor"],
    "views": "44k"
  },
  {
    "name": "ASCII Tools",
    "desc": "Various ASCII conversion tools including ASCII to Base64, Base64 to ASCII, Byte to ASCII, Image to ASCII Art, ASCII to Text, Text to ASCII, Char to ASCII, UTF8 to ASCII, Decimal to ASCII.",
    "slug": "ascii-tools",
    "logo": "",
    "link": "./tools/ascii-tools",
    "title": "ASCII Tools",
    "keywords": ["ASCII", "tools", "conversion"],
    "views": "45k"
  },
  {
    "name": "Base64 Tools",
    "desc": "A collection of tools related to Base64 encoding and decoding.",
    "slug": "base64-tools",
    "logo": "",
    "link": "./tools/base64-tools",
    "title": "Base64 Tools",
    "keywords": ["Base64", "tools", "encoding", "decoding"],
    "views": "46k"
  },
  {
    "name": "Cheat Sheets",
    "desc": "Various cheat sheets for different programming languages and technologies.",
    "slug": "cheat-sheets",
    "logo": "",
    "link": "./tools/cheat-sheets",
    "title": "Cheat Sheets",
    "keywords": ["cheat", "sheets", "programming", "languages", "technologies"],
    "views": "47k"
  }
]
